README
setup.py
openproximity_ext/__init__.py
openproximity_ext/static/css/cupertino/jquery-ui-1.8.16.custom.css
openproximity_ext/static/css/cupertino/images/ui-bg_flat_0_aaaaaa_40x100.png
openproximity_ext/static/css/cupertino/images/ui-bg_glass_55_fbf9ee_1x400.png
openproximity_ext/static/css/cupertino/images/ui-bg_glass_65_ffffff_1x400.png
openproximity_ext/static/css/cupertino/images/ui-bg_glass_75_dadada_1x400.png
openproximity_ext/static/css/cupertino/images/ui-bg_glass_75_e6e6e6_1x400.png
openproximity_ext/static/css/cupertino/images/ui-bg_glass_75_ffffff_1x400.png
openproximity_ext/static/css/cupertino/images/ui-bg_highlight-soft_75_cccccc_1x100.png
openproximity_ext/static/css/cupertino/images/ui-bg_inset-soft_95_fef1ec_1x100.png
openproximity_ext/static/css/cupertino/images/ui-icons_222222_256x240.png
openproximity_ext/static/css/cupertino/images/ui-icons_2e83ff_256x240.png
openproximity_ext/static/css/cupertino/images/ui-icons_454545_256x240.png
openproximity_ext/static/css/cupertino/images/ui-icons_888888_256x240.png
openproximity_ext/static/css/cupertino/images/ui-icons_cd0a0a_256x240.png
openproximity_ext/static/js/Base.js
openproximity_ext/static/js/DateTime.js
openproximity_ext/static/js/date.js
openproximity_ext/static/js/jquery-1.6.2.min.js
openproximity_ext/static/js/jquery-ui-1.8.16.min.js
openproximity_ext/static/js/jquery.corner.js
openproximity_ext/static/js/jquery.jstree.js
openproximity_ext/static/js/jquery.tweet.js
openproximity_ext/static/js/json2.js
openproximity_ext/static/js/open-flash-chart.js
openproximity_ext/static/js/swfobject.js
openproximity_ext/static/js/themes/default/d.gif
openproximity_ext/static/js/themes/default/d.png
openproximity_ext/static/js/themes/default/style.css
openproximity_ext/static/js/themes/default/throbber.gif
openproximity_ext/static/swf/open-flash-chart-full-embedded-font.swf
openproximity_ext/static/swf/open-flash-chart.swf
openproximity_external_media.egg-info/PKG-INFO
openproximity_external_media.egg-info/SOURCES.txt
openproximity_external_media.egg-info/dependency_links.txt
openproximity_external_media.egg-info/top_level.txt