Metadata-Version: 1.0
Name: openproximity-external-media
Version: 0.1.3
Summary: This is OpenProximity external metadata package
Home-page: https://github.com/OpenProximity/OpenProximity-web-3rdparty-static
Author: Naranjo Manuel Francisco
Author-email: manuel@aircable.net
License: UNKNOWN
Keywords: openproximity proximity marketing bluetooth static
Platform: UNKNOWN
